[
    {
        "heroId": "1-1",
        "skins": [
            {
                "name": "经典",
                "description": "猎鹰联邦初级佣兵装束。乍看毫无特色，容易淹没在人群中。凑近了才会发现，铠甲和武器都打磨得比别人更加光亮",
                "get": "默认",
                "price": "免费",
                "ikon": "image/skins/1-1/经典/立绘.png",
                "pics": [
                    {
                        "name": "无动作",
                        "pic": "image/skins/1-1/经典/无动作.png"
                    },
                    {
                        "name": "动作1",
                        "pic": "image/skins/1-1/经典/动作1.png"
                    },
                    {
                        "name": "动作2",
                        "pic": "image/skins/1-1/经典/动作2.png"
                    },
                    {
                        "name": "被攻击",
                        "pic": "image/skins/1-1/经典/被攻击.png"
                    },
                    {
                        "name": "EX效果",
                        "pic": "image/skins/1-1/经典/EX效果.png"
                    }
                ]
            },
            {
                "name": "青空",
                "description": "哇！是新皮肤！",
                "get": "商店",
                "price": "80钻石",
                "ikon": "image/skins/1-1/青空/立绘.png",
                "pics": [
                    {
                        "name": "无动作",
                        "pic": "image/skins/1-1/青空/无动作.png"
                    },
                    {
                        "name": "动作1",
                        "pic": "image/skins/1-1/青空/动作1.png"
                    },
                    {
                        "name": "动作2",
                        "pic": "image/skins/1-1/青空/动作2.png"
                    },
                    {
                        "name": "被攻击",
                        "pic": "image/skins/1-1/青空/被攻击.png"
                    }
                ]
            },
            {
                "name": "守护之誓",
                "description": "前路未知，唯一坚定的是心中誓言。曾经的小小少年，不知不觉间已可独当一面。“这套装束好像过于华丽了些，执行任务时会不会太显眼...不过...她开心就好，嘿嘿”",
                "get": "商店",
                "price": "待补充",
                "ikon": "image/skins/1-1/守护之誓/立绘.png",
                "pics": [
                    {
                        "name": "无动作",
                        "pic": "image/skins/1-1/守护之誓/无动作.png"
                    },
                    {
                        "name": "动作1",
                        "pic": "image/skins/1-1/守护之誓/动作1.png"
                    },
                    {
                        "name": "动作2",
                        "pic": "image/skins/1-1/守护之誓/动作2.png"
                    },
                    {
                        "name": "被攻击",
                        "pic": "image/skins/1-1/守护之誓/被攻击.png"
                    },
                    {
                        "name": "EX效果",
                        "pic": "image/skins/1-1/守护之誓/EX效果.png"
                    }
                ]
            }
        ]
    },
    {
        "heroId": "1-2",
        "skins": [
            {
                "name": "经典",
                "description": "英雄的经典皮肤。虽然看起来比较简朴，但是还是很实用的。",
                "get": "默认",
                "price": "免费",
                "ikon": "image/skins/1-2/经典/立绘.png",
                "pics": [
                    {
                        "name": "无动作",
                        "pic": "image/skins/1-2/经典/无动作.png"
                    },
                    {
                        "name": "动作1",
                        "pic": "image/skins/1-2/经典/动作1.png"
                    },
                    {
                        "name": "动作2",
                        "pic": "image/skins/1-2/经典/动作2.png"
                    },
                    {
                        "name": "被攻击",
                        "pic": "image/skins/1-2/经典/被攻击.png"
                    },
                    {
                        "name": "EX效果",
                        "pic": "image/skins/1-2/经典/EX效果.png"
                    },
                    {
                        "name": "技能2效果",
                        "pic": "image/skins/1-2/经典/技能2效果.png"
                    }
                ]
            }
        ]
    },
    {
        "heroId": "1-3",
        "skins": [
            {
                "name": "经典",
                "description": "英雄的经典皮肤。虽然看起来比较简朴，但是还是很实用的。",
                "get": "默认",
                "price": "免费",
                "ikon": "image/skins/1-3/经典/立绘.png",
                "pics": [
                    {
                        "name": "无动作",
                        "pic": "image/skins/1-3/经典/无动作.png"
                    },
                    {
                        "name": "动作1",
                        "pic": "image/skins/1-3/经典/动作1.png"
                    },
                    {
                        "name": "动作2",
                        "pic": "image/skins/1-3/经典/动作2.png"
                    },
                    {
                        "name": "被攻击",
                        "pic": "image/skins/1-3/经典/被攻击.png"
                    },
                    {
                        "name": "EX效果",
                        "pic": "image/skins/1-3/经典/EX效果.png"
                    }
                ]
            }
        ]
    },
    {
        "heroId": "1-4",
        "skins": [
            {
                "name": "经典",
                "description": "英雄的经典皮肤。虽然看起来比较简朴，但是还是很实用的。",
                "get": "默认",
                "price": "免费",
                "ikon": "image/skins/1-4/经典/立绘.png",
                "pics": [
                    {
                        "name": "无动作",
                        "pic": "image/skins/1-4/经典/无动作.png"
                    },
                    {
                        "name": "动作1",
                        "pic": "image/skins/1-4/经典/动作1.png"
                    },
                    {
                        "name": "动作2",
                        "pic": "image/skins/1-4/经典/动作2.png"
                    },
                    {
                        "name": "被攻击",
                        "pic": "image/skins/1-4/经典/被攻击.png"
                    },
                    {
                        "name": "EX效果",
                        "pic": "image/skins/1-4/经典/EX效果.png"
                    },
                    {
                        "name": "技能1效果",
                        "pic": "image/skins/1-4/经典/技能1效果.png"
                    }
                ]
            }
        ]
    },
    {
        "heroId": "1-5",
        "skins": [
            {
                "name": "经典",
                "description": "英雄的经典皮肤。虽然看起来比较简朴，但是还是很实用的。",
                "get": "默认",
                "price": "免费",
                "ikon": "image/skins/1-5/经典/立绘.png",
                "pics": [
                    {
                        "name": "无动作",
                        "pic": "image/skins/1-5/经典/无动作.png"
                    },
                    {
                        "name": "动作1",
                        "pic": "image/skins/1-5/经典/动作1.png"
                    },
                    {
                        "name": "动作2",
                        "pic": "image/skins/1-5/经典/动作2.png"
                    },
                    {
                        "name": "被攻击",
                        "pic": "image/skins/1-5/经典/被攻击.png"
                    },
                    {
                        "name": "EX效果",
                        "pic": "image/skins/1-5/经典/EX效果.png"
                    }
                ]
            }
        ]
    },
    {
        "heroId": "1-6",
        "skins": [
            {
                "name": "经典",
                "description": "英雄的经典皮肤。虽然看起来比较简朴，但是还是很实用的。",
                "get": "默认",
                "price": "免费",
                "ikon": "image/skins/1-6/经典/立绘.png",
                "pics": [
                    {
                        "name": "无动作",
                        "pic": "image/skins/1-6/经典/无动作.png"
                    },
                    {
                        "name": "动作1",
                        "pic": "image/skins/1-6/经典/动作1.png"
                    },
                    {
                        "name": "动作2",
                        "pic": "image/skins/1-6/经典/动作2.png"
                    },
                    {
                        "name": "被攻击",
                        "pic": "image/skins/1-6/经典/被攻击.png"
                    },
                    {
                        "name": "EX效果",
                        "pic": "image/skins/1-6/经典/EX效果.png"
                    },
                    {
                        "name": "技能1效果",
                        "pic": "image/skins/1-6/经典/技能1效果.png"
                    },
                    {
                        "name": "技能3效果",
                        "pic": "image/skins/1-6/经典/技能3效果.png"
                    }
                ]
            }
        ]
    },
    {
        "heroId": "1-7",
        "skins": [
            {
                "name": "经典",
                "description": "英雄的经典皮肤。虽然看起来比较简朴，但是还是很实用的。",
                "get": "默认",
                "price": "免费",
                "ikon": "image/skins/1-7/经典/立绘.png",
                "pics": [
                    {
                        "name": "无动作",
                        "pic": "image/skins/1-7/经典/无动作.png"
                    },
                    {
                        "name": "动作1",
                        "pic": "image/skins/1-7/经典/动作1.png"
                    },
                    {
                        "name": "动作2",
                        "pic": "image/skins/1-7/经典/动作2.png"
                    },
                    {
                        "name": "被攻击",
                        "pic": "image/skins/1-7/经典/被攻击.png"
                    },
                    {
                        "name": "EX效果",
                        "pic": "image/skins/1-7/经典/EX效果.png"
                    }
                ]
            }
        ]
    },
    {
        "heroId": "1-8",
        "skins": [
            {
                "name": "经典",
                "description": "英雄的经典皮肤。虽然看起来比较简朴，但是还是很实用的。",
                "get": "默认",
                "price": "免费",
                "ikon": "image/skins/1-8/经典/立绘.png",
                "pics": [
                    {
                        "name": "无动作",
                        "pic": "image/skins/1-8/经典/无动作.png"
                    },
                    {
                        "name": "动作1",
                        "pic": "image/skins/1-8/经典/动作1.png"
                    },
                    {
                        "name": "动作2",
                        "pic": "image/skins/1-8/经典/动作2.png"
                    },
                    {
                        "name": "被攻击",
                        "pic": "image/skins/1-8/经典/被攻击.png"
                    },
                    {
                        "name": "EX效果",
                        "pic": "image/skins/1-8/经典/EX效果.png"
                    },
                    {
                        "name": "技能1效果",
                        "pic": "image/skins/1-8/经典/技能1效果.png"
                    },
                    {
                        "name": "技能3效果",
                        "pic": "image/skins/1-8/经典/技能3效果.png"
                    }
                ]
            }
        ]
    },
    {
        "heroId": "1-9",
        "skins": [
            {
                "name": "经典",
                "description": "英雄的经典皮肤。虽然看起来比较简朴，但是还是很实用的。",
                "get": "默认",
                "price": "免费",
                "ikon": "image/skins/1-9/经典/立绘.png",
                "pics": [
                    {
                        "name": "无动作",
                        "pic": "image/skins/1-9/经典/无动作.png"
                    },
                    {
                        "name": "动作1",
                        "pic": "image/skins/1-9/经典/动作1.png"
                    },
                    {
                        "name": "动作2",
                        "pic": "image/skins/1-9/经典/动作2.png"
                    },
                    {
                        "name": "被攻击",
                        "pic": "image/skins/1-9/经典/被攻击.png"
                    },
                    {
                        "name": "EX效果",
                        "pic": "image/skins/1-9/经典/EX效果.png"
                    }
                ]
            }
        ]
    },
    {
        "heroId": "1-10",
        "skins": [
            {
                "name": "经典",
                "description": "英雄的经典皮肤。虽然看起来比较简朴，但是还是很实用的。",
                "get": "默认",
                "price": "免费",
                "ikon": "image/skins/1-10/经典/立绘.png",
                "pics": [
                    {
                        "name": "无动作",
                        "pic": "image/skins/1-10/经典/无动作.png"
                    },
                    {
                        "name": "动作1",
                        "pic": "image/skins/1-10/经典/动作1.png"
                    },
                    {
                        "name": "动作2",
                        "pic": "image/skins/1-10/经典/动作2.png"
                    },
                    {
                        "name": "被攻击",
                        "pic": "image/skins/1-10/经典/被攻击.png"
                    },
                    {
                        "name": "EX效果",
                        "pic": "image/skins/1-10/经典/EX效果.png"
                    },
                    {
                        "name": "技能1效果",
                        "pic": "image/skins/1-10/经典/技能1效果.png"
                    }
                ]
            }
        ]
    },
    {
        "heroId": "2-1",
        "skins": [
            {
                "name": "经典",
                "description": "英雄的经典皮肤。虽然看起来比较简朴，但是还是很实用的。",
                "get": "默认",
                "price": "免费",
                "ikon": "image/skins/2-1/经典/立绘.png",
                "pics": [
                    {
                        "name": "无动作",
                        "pic": "image/skins/2-1/经典/无动作.png"
                    },
                    {
                        "name": "动作1",
                        "pic": "image/skins/2-1/经典/动作1.png"
                    },
                    {
                        "name": "动作2",
                        "pic": "image/skins/2-1/经典/动作2.png"
                    },
                    {
                        "name": "被攻击",
                        "pic": "image/skins/2-1/经典/被攻击.png"
                    },
                    {
                        "name": "EX效果",
                        "pic": "image/skins/2-1/经典/EX效果.png"
                    },
                    {
                        "name": "技能2效果",
                        "pic": "image/skins/2-1/经典/技能2效果.png"
                    }
                ]
            }
        ]
    },
    {
        "heroId": "2-2",
        "skins": [
            {
                "name": "经典",
                "description": "英雄的经典皮肤。虽然看起来比较简朴，但是还是很实用的。",
                "get": "默认",
                "price": "免费",
                "ikon": "image/skins/2-2/经典/立绘.png",
                "pics": [
                    {
                        "name": "无动作",
                        "pic": "image/skins/2-2/经典/无动作.png"
                    },
                    {
                        "name": "动作1",
                        "pic": "image/skins/2-2/经典/动作1.png"
                    },
                    {
                        "name": "动作2",
                        "pic": "image/skins/2-2/经典/动作2.png"
                    },
                    {
                        "name": "被攻击",
                        "pic": "image/skins/2-2/经典/被攻击.png"
                    },
                    {
                        "name": "EX效果",
                        "pic": "image/skins/2-2/经典/EX效果.png"
                    }
                ]
            }
        ]
    },
    {
        "heroId": "2-3",
        "skins": [
            {
                "name": "经典",
                "description": "英雄的经典皮肤。虽然看起来比较简朴，但是还是很实用的。",
                "get": "默认",
                "price": "免费",
                "ikon": "image/skins/2-3/经典/立绘.png",
                "pics": [
                    {
                        "name": "无动作",
                        "pic": "image/skins/2-3/经典/无动作.png"
                    },
                    {
                        "name": "动作1",
                        "pic": "image/skins/2-3/经典/动作1.png"
                    },
                    {
                        "name": "动作2",
                        "pic": "image/skins/2-3/经典/动作2.png"
                    },
                    {
                        "name": "被攻击",
                        "pic": "image/skins/2-3/经典/被攻击.png"
                    },
                    {
                        "name": "EX效果",
                        "pic": "image/skins/2-3/经典/EX效果.png"
                    }
                ]
            }
        ]
    },
    {
        "heroId": "2-4",
        "skins": [
            {
                "name": "经典",
                "description": "英雄的经典皮肤。虽然看起来比较简朴，但是还是很实用的。",
                "get": "默认",
                "price": "免费",
                "ikon": "image/skins/2-4/经典/立绘.png",
                "pics": [
                    {
                        "name": "无动作",
                        "pic": "image/skins/2-4/经典/无动作.png"
                    },
                    {
                        "name": "动作1",
                        "pic": "image/skins/2-4/经典/动作1.png"
                    },
                    {
                        "name": "动作2",
                        "pic": "image/skins/2-4/经典/动作2.png"
                    },
                    {
                        "name": "被攻击",
                        "pic": "image/skins/2-4/经典/被攻击.png"
                    },
                    {
                        "name": "EX效果",
                        "pic": "image/skins/2-4/经典/EX效果.png"
                    },
                    {
                        "name": "技能1效果",
                        "pic": "image/skins/2-4/经典/技能1效果.png"
                    },
                    {
                        "name": "技能3效果",
                        "pic": "image/skins/2-4/经典/技能3效果.png"
                    }
                ]
            }
        ]
    },
    {
        "heroId": "2-5",
        "skins": [
            {
                "name": "经典",
                "description": "英雄的经典皮肤。虽然看起来比较简朴，但是还是很实用的。",
                "get": "默认",
                "price": "免费",
                "ikon": "image/skins/2-5/经典/立绘.png",
                "pics": [
                    {
                        "name": "无动作",
                        "pic": "image/skins/2-5/经典/无动作.png"
                    },
                    {
                        "name": "动作1",
                        "pic": "image/skins/2-5/经典/动作1.png"
                    },
                    {
                        "name": "动作2",
                        "pic": "image/skins/2-5/经典/动作2.png"
                    },
                    {
                        "name": "被攻击",
                        "pic": "image/skins/2-5/经典/被攻击.png"
                    },
                    {
                        "name": "EX效果",
                        "pic": "image/skins/2-5/经典/EX效果.png"
                    },
                    {
                        "name": "技能1效果",
                        "pic": "image/skins/2-5/经典/技能1效果.png"
                    }
                ]
            }
        ]
    },
    {
        "heroId": "2-6",
        "skins": [
            {
                "name": "经典",
                "description": "英雄的经典皮肤。虽然看起来比较简朴，但是还是很实用的。",
                "get": "默认",
                "price": "免费",
                "ikon": "image/skins/2-6/经典/立绘.png",
                "pics": [
                    {
                        "name": "无动作",
                        "pic": "image/skins/2-6/经典/无动作.png"
                    },
                    {
                        "name": "动作1",
                        "pic": "image/skins/2-6/经典/动作1.png"
                    },
                    {
                        "name": "动作2",
                        "pic": "image/skins/2-6/经典/动作2.png"
                    },
                    {
                        "name": "被攻击",
                        "pic": "image/skins/2-6/经典/被攻击.png"
                    },
                    {
                        "name": "EX效果",
                        "pic": "image/skins/2-6/经典/EX效果.png"
                    },
                    {
                        "name": "技能2效果",
                        "pic": "image/skins/2-6/经典/技能2效果.png"
                    }
                ]
            }
        ]
    },
    {
        "heroId": "2-7",
        "skins": [
            {
                "name": "经典",
                "description": "英雄的经典皮肤。虽然看起来比较简朴，但是还是很实用的。",
                "get": "默认",
                "price": "免费",
                "ikon": "image/skins/2-7/经典/立绘.png",
                "pics": [
                    {
                        "name": "无动作",
                        "pic": "image/skins/2-7/经典/无动作.png"
                    },
                    {
                        "name": "动作1",
                        "pic": "image/skins/2-7/经典/动作1.png"
                    },
                    {
                        "name": "动作2",
                        "pic": "image/skins/2-7/经典/动作2.png"
                    },
                    {
                        "name": "被攻击",
                        "pic": "image/skins/2-7/经典/被攻击.png"
                    },
                    {
                        "name": "EX效果",
                        "pic": "image/skins/2-7/经典/EX效果.png"
                    },
                    {
                        "name": "技能2效果",
                        "pic": "image/skins/2-7/经典/技能2效果.png"
                    }
                ]
            }
        ]
    },
    {
        "heroId": "2-8",
        "skins": [
            {
                "name": "经典",
                "description": "英雄的经典皮肤。虽然看起来比较简朴，但是还是很实用的。",
                "get": "默认",
                "price": "免费",
                "ikon": "image/skins/2-8/经典/立绘.png",
                "pics": [
                    {
                        "name": "无动作",
                        "pic": "image/skins/2-8/经典/无动作.png"
                    },
                    {
                        "name": "动作1",
                        "pic": "image/skins/2-8/经典/动作1.png"
                    },
                    {
                        "name": "动作2",
                        "pic": "image/skins/2-8/经典/动作2.png"
                    },
                    {
                        "name": "被攻击",
                        "pic": "image/skins/2-8/经典/被攻击.png"
                    },
                    {
                        "name": "EX效果",
                        "pic": "image/skins/2-8/经典/EX效果.png"
                    }
                ]
            }
        ]
    },
    {
        "heroId": "2-9",
        "skins": [
            {
                "name": "经典",
                "description": "英雄的经典皮肤。虽然看起来比较简朴，但是还是很实用的。",
                "get": "默认",
                "price": "免费",
                "ikon": "image/skins/2-9/经典/立绘.png",
                "pics": [
                    {
                        "name": "无动作",
                        "pic": "image/skins/2-9/经典/无动作.png"
                    },
                    {
                        "name": "动作1",
                        "pic": "image/skins/2-9/经典/动作1.png"
                    },
                    {
                        "name": "动作2",
                        "pic": "image/skins/2-9/经典/动作2.png"
                    },
                    {
                        "name": "被攻击",
                        "pic": "image/skins/2-9/经典/被攻击.png"
                    },
                    {
                        "name": "EX效果",
                        "pic": "image/skins/2-9/经典/EX效果.png"
                    },
                    {
                        "name": "技能1效果",
                        "pic": "image/skins/2-9/经典/技能1效果.png"
                    }
                ]
            }
        ]
    },
    {
        "heroId": "2-10",
        "skins": [
            {
                "name": "经典",
                "description": "英雄的经典皮肤。虽然看起来比较简朴，但是还是很实用的。",
                "get": "默认",
                "price": "免费",
                "ikon": "image/skins/2-10/经典/立绘.png",
                "pics": [
                    {
                        "name": "无动作",
                        "pic": "image/skins/2-10/经典/无动作.png"
                    },
                    {
                        "name": "动作1",
                        "pic": "image/skins/2-10/经典/动作1.png"
                    },
                    {
                        "name": "动作2",
                        "pic": "image/skins/2-10/经典/动作2.png"
                    },
                    {
                        "name": "被攻击",
                        "pic": "image/skins/2-10/经典/被攻击.png"
                    },
                    {
                        "name": "EX效果",
                        "pic": "image/skins/2-10/经典/EX效果.png"
                    }
                ]
            }
        ]
    },
    {
        "heroId": "2-11",
        "skins": [
            {
                "name": "经典",
                "description": "英雄的经典皮肤。虽然看起来比较简朴，但是还是很实用的。",
                "get": "默认",
                "price": "免费",
                "ikon": "image/skins/2-11/经典/立绘.png",
                "pics": [
                    {
                        "name": "无动作",
                        "pic": "image/skins/2-11/经典/无动作.png"
                    },
                    {
                        "name": "动作1",
                        "pic": "image/skins/2-11/经典/动作1.png"
                    },
                    {
                        "name": "动作2",
                        "pic": "image/skins/2-11/经典/动作2.png"
                    },
                    {
                        "name": "被攻击",
                        "pic": "image/skins/2-11/经典/被攻击.png"
                    },
                    {
                        "name": "EX效果",
                        "pic": "image/skins/2-11/经典/EX效果.png"
                    },
                    {
                        "name": "技能1效果",
                        "pic": "image/skins/2-11/经典/技能1效果.png"
                    },
                    {
                        "name": "衍生1效果",
                        "pic": "image/skins/2-11/经典/衍生1效果.png"
                    },
                    {
                        "name": "衍生2效果",
                        "pic": "image/skins/2-11/经典/衍生2效果.png"
                    },
                    {
                        "name": "衍生3效果",
                        "pic": "image/skins/2-11/经典/衍生3效果.png"
                    }
                ]
            }
        ]
    },
    {
        "heroId": "3-1",
        "skins": [
            {
                "name": "经典",
                "description": "英雄的经典皮肤。虽然看起来比较简朴，但是还是很实用的。",
                "get": "默认",
                "price": "免费",
                "ikon": "image/skins/3-1/经典/立绘.png",
                "pics": [
                    {
                        "name": "无动作",
                        "pic": "image/skins/3-1/经典/无动作.png"
                    },
                    {
                        "name": "动作1",
                        "pic": "image/skins/3-1/经典/动作1.png"
                    },
                    {
                        "name": "动作2",
                        "pic": "image/skins/3-1/经典/动作2.png"
                    },
                    {
                        "name": "被攻击",
                        "pic": "image/skins/3-1/经典/被攻击.png"
                    },
                    {
                        "name": "EX效果",
                        "pic": "image/skins/3-1/经典/EX效果.png"
                    }
                ]
            }
        ]
    },
    {
        "heroId": "3-2",
        "skins": [
            {
                "name": "经典",
                "description": "英雄的经典皮肤。虽然看起来比较简朴，但是还是很实用的。",
                "get": "默认",
                "price": "免费",
                "ikon": "image/skins/3-2/经典/立绘.png",
                "pics": [
                    {
                        "name": "无动作",
                        "pic": "image/skins/3-2/经典/无动作.png"
                    },
                    {
                        "name": "动作1",
                        "pic": "image/skins/3-2/经典/动作1.png"
                    },
                    {
                        "name": "动作2",
                        "pic": "image/skins/3-2/经典/动作2.png"
                    },
                    {
                        "name": "被攻击",
                        "pic": "image/skins/3-2/经典/被攻击.png"
                    },
                    {
                        "name": "EX效果",
                        "pic": "image/skins/3-2/经典/EX效果.png"
                    },
                    {
                        "name": "技能3效果",
                        "pic": "image/skins/3-2/经典/技能3效果.png"
                    }
                ]
            }
        ]
    },
    {
        "heroId": "3-3",
        "skins": [
            {
                "name": "经典",
                "description": "英雄的经典皮肤。虽然看起来比较简朴，但是还是很实用的。",
                "get": "默认",
                "price": "免费",
                "ikon": "image/skins/3-3/经典/立绘.png",
                "pics": [
                    {
                        "name": "无动作",
                        "pic": "image/skins/3-3/经典/无动作.png"
                    },
                    {
                        "name": "动作1",
                        "pic": "image/skins/3-3/经典/动作1.png"
                    },
                    {
                        "name": "动作2",
                        "pic": "image/skins/3-3/经典/动作2.png"
                    },
                    {
                        "name": "被攻击",
                        "pic": "image/skins/3-3/经典/被攻击.png"
                    },
                    {
                        "name": "EX效果",
                        "pic": "image/skins/3-3/经典/EX效果.png"
                    },
                    {
                        "name": "技能2效果",
                        "pic": "image/skins/3-3/经典/技能2效果.png"
                    }
                ]
            }
        ]
    },
    {
        "heroId": "3-4",
        "skins": [
            {
                "name": "经典",
                "description": "英雄的经典皮肤。虽然看起来比较简朴，但是还是很实用的。",
                "get": "默认",
                "price": "免费",
                "ikon": "image/skins/3-4/经典/立绘.png",
                "pics": [
                    {
                        "name": "无动作",
                        "pic": "image/skins/3-4/经典/无动作.png"
                    },
                    {
                        "name": "动作1",
                        "pic": "image/skins/3-4/经典/动作1.png"
                    },
                    {
                        "name": "动作2",
                        "pic": "image/skins/3-4/经典/动作2.png"
                    },
                    {
                        "name": "被攻击",
                        "pic": "image/skins/3-4/经典/被攻击.png"
                    },
                    {
                        "name": "EX效果",
                        "pic": "image/skins/3-4/经典/EX效果.png"
                    },
                    {
                        "name": "技能2效果",
                        "pic": "image/skins/3-4/经典/技能2效果.png"
                    },
                    {
                        "name": "技能3效果",
                        "pic": "image/skins/3-4/经典/技能3效果.png"
                    }
                ]
            }
        ]
    },
    {
        "heroId": "3-5",
        "skins": [
            {
                "name": "经典",
                "description": "英雄的经典皮肤。虽然看起来比较简朴，但是还是很实用的。",
                "get": "默认",
                "price": "免费",
                "ikon": "image/skins/3-5/经典/立绘.png",
                "pics": [
                    {
                        "name": "无动作",
                        "pic": "image/skins/3-5/经典/无动作.png"
                    },
                    {
                        "name": "动作1",
                        "pic": "image/skins/3-5/经典/动作1.png"
                    },
                    {
                        "name": "动作2",
                        "pic": "image/skins/3-5/经典/动作2.png"
                    },
                    {
                        "name": "被攻击",
                        "pic": "image/skins/3-5/经典/被攻击.png"
                    },
                    {
                        "name": "EX效果",
                        "pic": "image/skins/3-5/经典/EX效果.png"
                    },
                    {
                        "name": "技能2效果",
                        "pic": "image/skins/3-5/经典/技能2效果.png"
                    },
                    {
                        "name": "技能3效果",
                        "pic": "image/skins/3-5/经典/技能3效果.png"
                    }
                ]
            }
        ]
    },
    {
        "heroId": "3-6",
        "skins": [
            {
                "name": "经典",
                "description": "英雄的经典皮肤。虽然看起来比较简朴，但是还是很实用的。",
                "get": "默认",
                "price": "免费",
                "ikon": "image/skins/3-6/经典/立绘.png",
                "pics": [
                    {
                        "name": "无动作",
                        "pic": "image/skins/3-6/经典/无动作.png"
                    },
                    {
                        "name": "动作1",
                        "pic": "image/skins/3-6/经典/动作1.png"
                    },
                    {
                        "name": "动作2",
                        "pic": "image/skins/3-6/经典/动作2.png"
                    },
                    {
                        "name": "被攻击",
                        "pic": "image/skins/3-6/经典/被攻击.png"
                    },
                    {
                        "name": "EX效果",
                        "pic": "image/skins/3-6/经典/EX效果.png"
                    },
                    {
                        "name": "技能2效果",
                        "pic": "image/skins/3-6/经典/技能2效果.png"
                    }
                ]
            }
        ]
    },
    {
        "heroId": "3-7",
        "skins": [
            {
                "name": "经典",
                "description": "英雄的经典皮肤。虽然看起来比较简朴，但是还是很实用的。",
                "get": "默认",
                "price": "免费",
                "ikon": "image/skins/3-7/经典/立绘.png",
                "pics": [
                    {
                        "name": "无动作",
                        "pic": "image/skins/3-7/经典/无动作.png"
                    },
                    {
                        "name": "动作1",
                        "pic": "image/skins/3-7/经典/动作1.png"
                    },
                    {
                        "name": "动作2",
                        "pic": "image/skins/3-7/经典/动作2.png"
                    },
                    {
                        "name": "被攻击",
                        "pic": "image/skins/3-7/经典/被攻击.png"
                    },
                    {
                        "name": "EX效果",
                        "pic": "image/skins/3-7/经典/EX效果.png"
                    },
                    {
                        "name": "技能1效果",
                        "pic": "image/skins/3-7/经典/技能1效果.png"
                    }
                ]
            }
        ]
    },
    {
        "heroId": "3-8",
        "skins": [
            {
                "name": "经典",
                "description": "英雄的经典皮肤。虽然看起来比较简朴，但是还是很实用的。",
                "get": "默认",
                "price": "免费",
                "ikon": "image/skins/3-8/经典/立绘.png",
                "pics": [
                    {
                        "name": "无动作",
                        "pic": "image/skins/3-8/经典/无动作.png"
                    },
                    {
                        "name": "动作1",
                        "pic": "image/skins/3-8/经典/动作1.png"
                    },
                    {
                        "name": "动作2",
                        "pic": "image/skins/3-8/经典/动作2.png"
                    },
                    {
                        "name": "被攻击",
                        "pic": "image/skins/3-8/经典/被攻击.png"
                    },
                    {
                        "name": "EX效果",
                        "pic": "image/skins/3-8/经典/EX效果.png"
                    },
                    {
                        "name": "技能3效果",
                        "pic": "image/skins/3-8/经典/技能3效果.png"
                    }
                ]
            }
        ]
    },
    {
        "heroId": "3-9",
        "skins": [
            {
                "name": "经典",
                "description": "英雄的经典皮肤。虽然看起来比较简朴，但是还是很实用的。",
                "get": "默认",
                "price": "免费",
                "ikon": "image/skins/3-9/经典/立绘.png",
                "pics": [
                    {
                        "name": "无动作",
                        "pic": "image/skins/3-9/经典/无动作.png"
                    },
                    {
                        "name": "动作1",
                        "pic": "image/skins/3-9/经典/动作1.png"
                    },
                    {
                        "name": "动作2",
                        "pic": "image/skins/3-9/经典/动作2.png"
                    },
                    {
                        "name": "被攻击",
                        "pic": "image/skins/3-9/经典/被攻击.png"
                    },
                    {
                        "name": "EX效果",
                        "pic": "image/skins/3-9/经典/EX效果.png"
                    }
                ]
            }
        ]
    },
    {
        "heroId": "4-1",
        "skins": [
            {
                "name": "经典",
                "description": "黎明守护初级牧师装束。看上去有些旧了，应该是从别的牧师那里继承来的。经过波妮巧手设计和调整后，还算合身。",
                "get": "默认",
                "price": "免费",
                "ikon": "image/skins/4-1/经典/立绘.png",
                "pics": [
                    {
                        "name": "无动作",
                        "pic": "image/skins/4-1/经典/无动作.png"
                    },
                    {
                        "name": "动作1",
                        "pic": "image/skins/4-1/经典/动作1.png"
                    },
                    {
                        "name": "动作2",
                        "pic": "image/skins/4-1/经典/动作2.png"
                    },
                    {
                        "name": "被攻击",
                        "pic": "image/skins/4-1/经典/被攻击.png"
                    },
                    {
                        "name": "EX效果",
                        "pic": "image/skins/4-1/经典/EX效果.png"
                    },
                    {
                        "name": "技能3效果",
                        "pic": "image/skins/4-1/经典/技能3效果.png"
                    }
                ]
            }
        ]
    },
    {
        "heroId": "4-2",
        "skins": [
            {
                "name": "经典",
                "description": "英雄的经典皮肤。虽然看起来比较简朴，但是还是很实用的。",
                "get": "默认",
                "price": "免费",
                "ikon": "image/skins/4-2/经典/立绘.png",
                "pics": [
                    {
                        "name": "无动作",
                        "pic": "image/skins/4-2/经典/无动作.png"
                    },
                    {
                        "name": "动作1",
                        "pic": "image/skins/4-2/经典/动作1.png"
                    },
                    {
                        "name": "动作2",
                        "pic": "image/skins/4-2/经典/动作2.png"
                    },
                    {
                        "name": "被攻击",
                        "pic": "image/skins/4-2/经典/被攻击.png"
                    },
                    {
                        "name": "EX效果",
                        "pic": "image/skins/4-2/经典/EX效果.png"
                    },
                    {
                        "name": "技能1效果",
                        "pic": "image/skins/4-2/经典/技能1效果.png"
                    }
                ]
            }
        ]
    },
    {
        "heroId": "4-3",
        "skins": [
            {
                "name": "经典",
                "description": "英雄的经典皮肤。虽然看起来比较简朴，但是还是很实用的。",
                "get": "默认",
                "price": "免费",
                "ikon": "image/skins/4-3/经典/立绘.png",
                "pics": [
                    {
                        "name": "无动作",
                        "pic": "image/skins/4-3/经典/无动作.png"
                    },
                    {
                        "name": "动作1",
                        "pic": "image/skins/4-3/经典/动作1.png"
                    },
                    {
                        "name": "动作2",
                        "pic": "image/skins/4-3/经典/动作2.png"
                    },
                    {
                        "name": "被攻击",
                        "pic": "image/skins/4-3/经典/被攻击.png"
                    },
                    {
                        "name": "EX效果",
                        "pic": "image/skins/4-3/经典/EX效果.png"
                    }
                ]
            }
        ]
    },
    {
        "heroId": "4-4",
        "skins": [
            {
                "name": "经典",
                "description": "英雄的经典皮肤。虽然看起来比较简朴，但是还是很实用的。",
                "get": "默认",
                "price": "免费",
                "ikon": "image/skins/4-4/经典/立绘.png",
                "pics": [
                    {
                        "name": "无动作",
                        "pic": "image/skins/4-4/经典/无动作.png"
                    },
                    {
                        "name": "动作1",
                        "pic": "image/skins/4-4/经典/动作1.png"
                    },
                    {
                        "name": "动作2",
                        "pic": "image/skins/4-4/经典/动作2.png"
                    },
                    {
                        "name": "被攻击",
                        "pic": "image/skins/4-4/经典/被攻击.png"
                    },
                    {
                        "name": "EX效果",
                        "pic": "image/skins/4-4/经典/EX效果.png"
                    },
                    {
                        "name": "技能3效果",
                        "pic": "image/skins/4-4/经典/技能3效果.png"
                    }
                ]
            }
        ]
    },
    {
        "heroId": "4-5",
        "skins": [
            {
                "name": "经典",
                "description": "英雄的经典皮肤。虽然看起来比较简朴，但是还是很实用的。",
                "get": "默认",
                "price": "免费",
                "ikon": "image/skins/4-5/经典/立绘.png",
                "pics": [
                    {
                        "name": "无动作",
                        "pic": "image/skins/4-5/经典/无动作.png"
                    },
                    {
                        "name": "动作1",
                        "pic": "image/skins/4-5/经典/动作1.png"
                    },
                    {
                        "name": "动作2",
                        "pic": "image/skins/4-5/经典/动作2.png"
                    },
                    {
                        "name": "被攻击",
                        "pic": "image/skins/4-5/经典/被攻击.png"
                    },
                    {
                        "name": "EX效果",
                        "pic": "image/skins/4-5/经典/EX效果.png"
                    },
                    {
                        "name": "技能1效果",
                        "pic": "image/skins/4-5/经典/技能1效果.png"
                    },
                    {
                        "name": "技能2效果",
                        "pic": "image/skins/4-5/经典/技能2效果.png"
                    },
                    {
                        "name": "技能3效果",
                        "pic": "image/skins/4-5/经典/技能3效果.png"
                    }
                ]
            }
        ]
    },
    {
        "heroId": "4-6",
        "skins": [
            {
                "name": "经典",
                "description": "英雄的经典皮肤。虽然看起来比较简朴，但是还是很实用的。",
                "get": "默认",
                "price": "免费",
                "ikon": "image/skins/4-6/经典/立绘.png",
                "pics": [
                    {
                        "name": "无动作",
                        "pic": "image/skins/4-6/经典/无动作.png"
                    },
                    {
                        "name": "动作1",
                        "pic": "image/skins/4-6/经典/动作1.png"
                    },
                    {
                        "name": "动作2",
                        "pic": "image/skins/4-6/经典/动作2.png"
                    },
                    {
                        "name": "被攻击",
                        "pic": "image/skins/4-6/经典/被攻击.png"
                    },
                    {
                        "name": "EX效果",
                        "pic": "image/skins/4-6/经典/EX效果.png"
                    },
                    {
                        "name": "技能3效果",
                        "pic": "image/skins/4-6/经典/技能3效果.png"
                    }
                ]
            }
        ]
    },
    {
        "heroId": "4-7",
        "skins": [
            {
                "name": "经典",
                "description": "英雄的经典皮肤。虽然看起来比较简朴，但是还是很实用的。",
                "get": "默认",
                "price": "免费",
                "ikon": "image/skins/4-7/经典/立绘.png",
                "pics": [
                    {
                        "name": "无动作",
                        "pic": "image/skins/4-7/经典/无动作.png"
                    },
                    {
                        "name": "动作1",
                        "pic": "image/skins/4-7/经典/动作1.png"
                    },
                    {
                        "name": "动作2",
                        "pic": "image/skins/4-7/经典/动作2.png"
                    },
                    {
                        "name": "被攻击",
                        "pic": "image/skins/4-7/经典/被攻击.png"
                    },
                    {
                        "name": "EX效果",
                        "pic": "image/skins/4-7/经典/EX效果.png"
                    },
                    {
                        "name": "技能3效果",
                        "pic": "image/skins/4-7/经典/技能3效果.png"
                    }
                ]
            }
        ]
    },
    {
        "heroId": "4-8",
        "skins": [
            {
                "name": "经典",
                "description": "英雄的经典皮肤。虽然看起来比较简朴，但是还是很实用的。",
                "get": "默认",
                "price": "免费",
                "ikon": "image/skins/4-8/经典/立绘.png",
                "pics": [
                    {
                        "name": "无动作",
                        "pic": "image/skins/4-8/经典/无动作.png"
                    },
                    {
                        "name": "动作1",
                        "pic": "image/skins/4-8/经典/动作1.png"
                    },
                    {
                        "name": "动作2",
                        "pic": "image/skins/4-8/经典/动作2.png"
                    },
                    {
                        "name": "被攻击",
                        "pic": "image/skins/4-8/经典/被攻击.png"
                    },
                    {
                        "name": "EX效果",
                        "pic": "image/skins/4-8/经典/EX效果.png"
                    }
                ]
            }
        ]
    },
    {
        "heroId": "5-1",
        "skins": [
            {
                "name": "经典",
                "description": "英雄的经典皮肤。虽然看起来比较简朴，但是还是很实用的。",
                "get": "默认",
                "price": "免费",
                "ikon": "image/skins/5-1/经典/立绘.png",
                "pics": [
                    {
                        "name": "无动作",
                        "pic": "image/skins/5-1/经典/无动作.png"
                    },
                    {
                        "name": "动作1",
                        "pic": "image/skins/5-1/经典/动作1.png"
                    },
                    {
                        "name": "动作2",
                        "pic": "image/skins/5-1/经典/动作2.png"
                    },
                    {
                        "name": "被攻击",
                        "pic": "image/skins/5-1/经典/被攻击.png"
                    },
                    {
                        "name": "EX效果",
                        "pic": "image/skins/5-1/经典/EX效果.png"
                    },
                    {
                        "name": "技能3效果",
                        "pic": "image/skins/5-1/经典/技能3效果.png"
                    }
                ]
            }
        ]
    },
    {
        "heroId": "5-2",
        "skins": [
            {
                "name": "经典",
                "description": "英雄的经典皮肤。虽然看起来比较简朴，但是还是很实用的。",
                "get": "默认",
                "price": "免费",
                "ikon": "image/skins/5-2/经典/立绘.png",
                "pics": [
                    {
                        "name": "无动作",
                        "pic": "image/skins/5-2/经典/无动作.png"
                    },
                    {
                        "name": "动作1",
                        "pic": "image/skins/5-2/经典/动作1.png"
                    },
                    {
                        "name": "动作2",
                        "pic": "image/skins/5-2/经典/动作2.png"
                    },
                    {
                        "name": "被攻击",
                        "pic": "image/skins/5-2/经典/被攻击.png"
                    },
                    {
                        "name": "EX效果",
                        "pic": "image/skins/5-2/经典/EX效果.png"
                    },
                    {
                        "name": "技能3效果",
                        "pic": "image/skins/5-2/经典/技能3效果.png"
                    }
                ]
            }
        ]
    },
    {
        "heroId": "5-3",
        "skins": [
            {
                "name": "经典",
                "description": "英雄的经典皮肤。虽然看起来比较简朴，但是还是很实用的。",
                "get": "默认",
                "price": "免费",
                "ikon": "image/skins/5-3/经典/立绘.png",
                "pics": [
                    {
                        "name": "无动作",
                        "pic": "image/skins/5-3/经典/无动作.png"
                    },
                    {
                        "name": "动作1",
                        "pic": "image/skins/5-3/经典/动作1.png"
                    },
                    {
                        "name": "动作2",
                        "pic": "image/skins/5-3/经典/动作2.png"
                    },
                    {
                        "name": "被攻击",
                        "pic": "image/skins/5-3/经典/被攻击.png"
                    },
                    {
                        "name": "EX效果",
                        "pic": "image/skins/5-3/经典/EX效果.png"
                    },
                    {
                        "name": "技能2效果",
                        "pic": "image/skins/5-3/经典/技能2效果.png"
                    }
                ]
            }
        ]
    },
    {
        "heroId": "5-4",
        "skins": [
            {
                "name": "经典",
                "description": "英雄的经典皮肤。虽然看起来比较简朴，但是还是很实用的。",
                "get": "默认",
                "price": "免费",
                "ikon": "image/skins/5-4/经典/立绘.png",
                "pics": [
                    {
                        "name": "无动作",
                        "pic": "image/skins/5-4/经典/无动作.png"
                    },
                    {
                        "name": "动作1",
                        "pic": "image/skins/5-4/经典/动作1.png"
                    },
                    {
                        "name": "动作2",
                        "pic": "image/skins/5-4/经典/动作2.png"
                    },
                    {
                        "name": "被攻击",
                        "pic": "image/skins/5-4/经典/被攻击.png"
                    },
                    {
                        "name": "EX效果",
                        "pic": "image/skins/5-4/经典/EX效果.png"
                    }
                ]
            }
        ]
    },
    {
        "heroId": "5-5",
        "skins": [
            {
                "name": "经典",
                "description": "英雄的经典皮肤。虽然看起来比较简朴，但是还是很实用的。",
                "get": "默认",
                "price": "免费",
                "ikon": "image/skins/5-5/经典/立绘.png",
                "pics": [
                    {
                        "name": "无动作",
                        "pic": "image/skins/5-5/经典/无动作.png"
                    },
                    {
                        "name": "动作1",
                        "pic": "image/skins/5-5/经典/动作1.png"
                    },
                    {
                        "name": "动作2",
                        "pic": "image/skins/5-5/经典/动作2.png"
                    },
                    {
                        "name": "被攻击",
                        "pic": "image/skins/5-5/经典/被攻击.png"
                    },
                    {
                        "name": "EX效果",
                        "pic": "image/skins/5-5/经典/EX效果.png"
                    },
                    {
                        "name": "技能1效果",
                        "pic": "image/skins/5-5/经典/技能1效果.png"
                    }
                ]
            }
        ]
    },
    {
        "heroId": "5-6",
        "skins": [
            {
                "name": "经典",
                "description": "英雄的经典皮肤。虽然看起来比较简朴，但是还是很实用的。",
                "get": "默认",
                "price": "免费",
                "ikon": "image/skins/5-6/经典/立绘.png",
                "pics": [
                    {
                        "name": "无动作",
                        "pic": "image/skins/5-6/经典/无动作.png"
                    },
                    {
                        "name": "动作1",
                        "pic": "image/skins/5-6/经典/动作1.png"
                    },
                    {
                        "name": "动作2",
                        "pic": "image/skins/5-6/经典/动作2.png"
                    },
                    {
                        "name": "被攻击",
                        "pic": "image/skins/5-6/经典/被攻击.png"
                    },
                    {
                        "name": "EX效果",
                        "pic": "image/skins/5-6/经典/EX效果.png"
                    },
                    {
                        "name": "技能1效果",
                        "pic": "image/skins/5-6/经典/技能1效果.png"
                    },
                    {
                        "name": "技能3效果",
                        "pic": "image/skins/5-6/经典/技能3效果.png"
                    }
                ]
            }
        ]
    },
    {
        "heroId": "5-7",
        "skins": [
            {
                "name": "经典",
                "description": "英雄的经典皮肤。虽然看起来比较简朴，但是还是很实用的。",
                "get": "默认",
                "price": "免费",
                "ikon": "image/skins/5-7/经典/立绘.png",
                "pics": [
                    {
                        "name": "无动作",
                        "pic": "image/skins/5-7/经典/无动作.png"
                    },
                    {
                        "name": "动作1",
                        "pic": "image/skins/5-7/经典/动作1.png"
                    },
                    {
                        "name": "动作2",
                        "pic": "image/skins/5-7/经典/动作2.png"
                    },
                    {
                        "name": "被攻击",
                        "pic": "image/skins/5-7/经典/被攻击.png"
                    },
                    {
                        "name": "EX效果",
                        "pic": "image/skins/5-7/经典/EX效果.png"
                    },
                    {
                        "name": "技能3效果",
                        "pic": "image/skins/5-7/经典/技能3效果.png"
                    }
                ]
            }
        ]
    },
    {
        "heroId": "5-8",
        "skins": [
            {
                "name": "经典",
                "description": "英雄的经典皮肤。虽然看起来比较简朴，但是还是很实用的。",
                "get": "默认",
                "price": "免费",
                "ikon": "image/skins/5-8/经典/立绘.png",
                "pics": [
                    {
                        "name": "无动作",
                        "pic": "image/skins/5-8/经典/无动作.png"
                    },
                    {
                        "name": "动作1",
                        "pic": "image/skins/5-8/经典/动作1.png"
                    },
                    {
                        "name": "动作2",
                        "pic": "image/skins/5-8/经典/动作2.png"
                    },
                    {
                        "name": "被攻击",
                        "pic": "image/skins/5-8/经典/被攻击.png"
                    },
                    {
                        "name": "EX效果",
                        "pic": "image/skins/5-8/经典/EX效果.png"
                    },
                    {
                        "name": "技能1效果",
                        "pic": "image/skins/5-8/经典/技能1效果.png"
                    }
                ]
            }
        ]
    },
    {
        "heroId": "5-9",
        "skins": [
            {
                "name": "经典",
                "description": "英雄的经典皮肤。虽然看起来比较简朴，但是还是很实用的。",
                "get": "默认",
                "price": "免费",
                "ikon": "image/skins/5-9/经典/立绘.png",
                "pics": [
                    {
                        "name": "无动作",
                        "pic": "image/skins/5-9/经典/无动作.png"
                    },
                    {
                        "name": "动作1",
                        "pic": "image/skins/5-9/经典/动作1.png"
                    },
                    {
                        "name": "动作2",
                        "pic": "image/skins/5-9/经典/动作2.png"
                    },
                    {
                        "name": "被攻击",
                        "pic": "image/skins/5-9/经典/被攻击.png"
                    },
                    {
                        "name": "EX效果",
                        "pic": "image/skins/5-9/经典/EX效果.png"
                    },
                    {
                        "name": "光芒闪耀效果",
                        "pic": "image/skins/5-9/经典/技能3效果.png"
                    }
                ]
            },
            {
                "name": "绿野仙踪",
                "description": "哇！是新皮肤！",
                "get": "商店",
                "price": "待补充",
                "ikon": "image/skins/5-9/绿野仙踪/立绘.png",
                "pics": [
                    {
                        "name": "无动作",
                        "pic": "image/skins/5-9/绿野仙踪/无动作.png"
                    },
                    {
                        "name": "动作1",
                        "pic": "image/skins/5-9/绿野仙踪/动作1.png"
                    },
                    {
                        "name": "动作2",
                        "pic": "image/skins/5-9/绿野仙踪/动作2.png"
                    },
                    {
                        "name": "被攻击",
                        "pic": "image/skins/5-9/绿野仙踪/被攻击.png"
                    },
                    {
                        "name": "EX效果",
                        "pic": "image/skins/5-9/绿野仙踪/EX效果.png"
                    }
                ]
            },
            {
                "name": "冰雪女王",
                "description": "哇！是新皮肤！",
                "get": "商店",
                "price": "待补充",
                "ikon": "image/skins/5-9/冰雪女王/立绘.png",
                "pics": [
                    {
                        "name": "无动作",
                        "pic": "image/skins/5-9/冰雪女王/无动作.png"
                    },
                    {
                        "name": "动作1",
                        "pic": "image/skins/5-9/冰雪女王/动作1.png"
                    },
                    {
                        "name": "动作2",
                        "pic": "image/skins/5-9/冰雪女王/动作2.png"
                    },
                    {
                        "name": "被攻击",
                        "pic": "image/skins/5-9/冰雪女王/被攻击.png"
                    },
                    {
                        "name": "EX效果",
                        "pic": "image/skins/5-9/冰雪女王/EX效果.png"
                    }
                ]
            },
            {
                "name": "幻月女王",
                "description": "哇！是新皮肤！",
                "get": "商店",
                "price": "待补充",
                "ikon": "image/skins/5-9/幻月女王/立绘.png",
                "pics": [
                    {
                        "name": "无动作",
                        "pic": "image/skins/5-9/幻月女王/无动作.png"
                    },
                    {
                        "name": "动作1",
                        "pic": "image/skins/5-9/幻月女王/动作1.png"
                    },
                    {
                        "name": "动作2",
                        "pic": "image/skins/5-9/幻月女王/动作2.png"
                    },
                    {
                        "name": "被攻击",
                        "pic": "image/skins/5-9/幻月女王/被攻击.png"
                    },
                    {
                        "name": "EX效果",
                        "pic": "image/skins/5-9/幻月女王/EX效果.png"
                    },
                    {
                        "name": "技能3效果",
                        "pic": "image/skins/5-9/幻月女王/技能3效果.png"
                    }
                ]
            },
            {
                "name": "月蚀女王",
                "description": "哇！是新皮肤！",
                "get": "商店",
                "price": "360钻石",
                "ikon": "image/skins/5-9/月蚀女王/立绘.png",
                "pics": [
                    {
                        "name": "无动作",
                        "pic": "image/skins/5-9/月蚀女王/无动作.png"
                    },
                    {
                        "name": "动作1",
                        "pic": "image/skins/5-9/月蚀女王/动作1.png"
                    },
                    {
                        "name": "动作2",
                        "pic": "image/skins/5-9/月蚀女王/动作2.png"
                    },
                    {
                        "name": "被攻击",
                        "pic": "image/skins/5-9/月蚀女王/被攻击.png"
                    },
                    {
                        "name": "EX效果",
                        "pic": "image/skins/5-9/月蚀女王/EX效果.png"
                    },
                    {
                        "name": "技能3效果",
                        "pic": "image/skins/5-9/月蚀女王/技能3效果.png"
                    }
                ]
            }
        ]
    },
    {
        "heroId": "5-10",
        "skins": [
            {
                "name": "经典",
                "description": "英雄的经典皮肤。虽然看起来比较简朴，但是还是很实用的。",
                "get": "默认",
                "price": "免费",
                "ikon": "image/skins/5-10/经典/立绘.png",
                "pics": [
                    {
                        "name": "无动作",
                        "pic": "image/skins/5-10/经典/无动作.png"
                    },
                    {
                        "name": "动作1",
                        "pic": "image/skins/5-10/经典/动作1.png"
                    },
                    {
                        "name": "动作2",
                        "pic": "image/skins/5-10/经典/动作2.png"
                    },
                    {
                        "name": "被攻击",
                        "pic": "image/skins/5-10/经典/被攻击.png"
                    },
                    {
                        "name": "EX效果",
                        "pic": "image/skins/5-10/经典/EX效果.png"
                    },
                    {
                        "name": "技能1效果",
                        "pic": "image/skins/5-10/经典/技能1效果.png"
                    }
                ]
            }
        ]
    },
    {
        "heroId": "5-11",
        "skins": [
            {
                "name": "经典",
                "description": "英雄的经典皮肤。虽然看起来比较简朴，但是还是很实用的。",
                "get": "默认",
                "price": "免费",
                "ikon": "image/skins/5-11/经典/立绘.png",
                "pics": [
                    {
                        "name": "无动作",
                        "pic": "image/skins/5-11/经典/无动作.png"
                    },
                    {
                        "name": "动作1",
                        "pic": "image/skins/5-11/经典/动作1.png"
                    },
                    {
                        "name": "动作2",
                        "pic": "image/skins/5-11/经典/动作2.png"
                    },
                    {
                        "name": "被攻击",
                        "pic": "image/skins/5-11/经典/被攻击.png"
                    },
                    {
                        "name": "EX效果",
                        "pic": "image/skins/5-11/经典/EX效果.png"
                    }
                ]
            }
        ]
    }
]
